{
  "main": {
    "id": "c1fc8f61ffc3d2b9",
    "type": "split",
    "children": [
      {
        "id": "687dc111abc50d74",
        "type": "tabs",
        "children": [
          {
            "id": "784c52e330e2ef48",
            "type": "leaf",
            "state": {
              "type": "markdown",
              "state": {
                "file": "docs/并行/算子加速思路/GEMM 算子调优.md",
                "mode": "source",
                "source": false
              }
            }
          },
          {
            "id": "d8fae19306f0adc4",
            "type": "leaf",
            "state": {
              "type": "markdown",
              "state": {
                "file": "docs/并行/算子加速思路/GEMM 算子调优.md",
                "mode": "source",
                "source": false
              }
            }
          }
        ],
        "currentTab": 1
      }
    ],
    "direction": "vertical"
  },
  "left": {
    "id": "0058d8fc1f814e96",
    "type": "split",
    "children": [
      {
        "id": "c6ed0773c2078476",
        "type": "tabs",
        "children": [
          {
            "id": "f16fe43bdf1b26fb",
            "type": "leaf",
            "state": {
              "type": "file-explorer",
              "state": {
                "sortOrder": "alphabetical"
              }
            }
          },
          {
            "id": "afdf89713d8d27e9",
            "type": "leaf",
            "state": {
              "type": "search",
              "state": {
                "query": "tag:#执行中",
                "matchingCase": false,
                "explainSearch": false,
                "collapseAll": false,
                "extraContext": false,
                "sortOrder": "alphabetical"
              }
            }
          },
          {
            "id": "b2ba2d257c6806ba",
            "type": "leaf",
            "state": {
              "type": "bookmarks",
              "state": {}
            }
          }
        ]
      }
    ],
    "direction": "horizontal",
    "width": 301.5,
    "collapsed": true
  },
  "right": {
    "id": "94d74886e9927f0e",
    "type": "split",
    "children": [
      {
        "id": "20c721e517f02d2d",
        "type": "tabs",
        "children": [
          {
            "id": "54a714d7a8da6b2f",
            "type": "leaf",
            "state": {
              "type": "backlink",
              "state": {
                "file": "docs/并行/算子加速思路/GEMM 算子调优.md",
                "collapseAll": false,
                "extraContext": false,
                "sortOrder": "alphabetical",
                "showSearch": false,
                "searchQuery": "",
                "backlinkCollapsed": false,
                "unlinkedCollapsed": false
              }
            }
          },
          {
            "id": "0a9610a525a6ca3c",
            "type": "leaf",
            "state": {
              "type": "calendar",
              "state": {}
            }
          },
          {
            "id": "998a0bd55f65ff7e",
            "type": "leaf",
            "state": {
              "type": "advanced-tables-toolbar",
              "state": {}
            }
          }
        ],
        "currentTab": 2
      }
    ],
    "direction": "horizontal",
    "width": 300,
    "collapsed": true
  },
  "left-ribbon": {
    "hiddenItems": {
      "switcher:Open quick switcher": false,
      "graph:Open graph view": false,
      "canvas:Create new canvas": false,
      "daily-notes:Open today's daily note": false,
      "command-palette:Open command palette": false,
      "markdown-importer:Open format converter": false,
      "table-editor-obsidian:Advanced Tables Toolbar": false,
      "templater-obsidian:Templater": false
    }
  },
  "active": "d8fae19306f0adc4",
  "lastOpenFiles": [
    "docs/并行/4. GPU 内存结构.md",
    "docs/并行/1. OpenCL.md",
    "docs/并行/3. 多线程.md",
    "docs/并行/算子加速思路/Reduce 算子调优.md",
    "docs/并行/算子加速思路/GEMM 算子调优.md",
    "docs/计算机网络/计算机网络微课堂/2. 数据链路层.md",
    "常见深度学习算子优化思路记录.canvas",
    "docs/Linux/1. Linux常用命令.md",
    "docs/并行/算子加速思路/Pasted image 20230815150206.png",
    "docs/并行/算子加速思路/Pasted.md",
    "docs/并行/算子加速思路/Pasted image 20230815145244.png",
    "docs/并行/算子加速思路/Pasted image 20230815145244 1.png",
    "docs/并行/算子加速思路/Pasted image 20230815114346.png",
    "docs/并行/算子加速思路/Pasted image 20230815114247.png",
    "docs/并行/算子加速思路/Pasted image 20230815113825.png",
    "docs/并行/CUDA/CUDA C++ Programming Guide.md",
    "docs/并行/算子加速思路",
    "docs/并行/CUDA/CUDA_C_Programming_Guide.pdf",
    "docs/并行/CUDA/Pasted image 20230808161005.png",
    "docs/并行/CUDA/Pasted image 20230808155928.png",
    "docs/并行/CUDA/Pasted image 20230808171058.png",
    "docs/计算机网络/11. TCP 状态机.md",
    "docs/并行/CUDA/Pasted image 20230808160936.png",
    "docs/并行/CUDA",
    "docs/Untitled",
    "docs/并行/README.md",
    "docs/计算机网络/2. TCP 三次握手，四次挥手.md",
    "docs/计算机网络/3. Get VS Post.md",
    "docs/计算机网络/1. TCP 和 UDP 的区别.md",
    "docs/公司/README.md",
    "Untitled",
    "docs/计算机网络/12. ping www.baidu.com 流程.md",
    "docs/计算机网络/10. TCP 连接失败怎么调试.md",
    "docs/计算机网络/计算机网络微课堂/images",
    "docs/计算机网络/10. 计算机网络微课堂.md",
    "docs/计算机网络/计算机网络微课堂/0. 概述.md",
    "docs/计算机网络/计算机网络微课堂/1. 物理层.md",
    "docs/计算机网络/计算机网络微课堂",
    "docs/计算机网络/9. TCP 流量控制.md",
    "docs/阿里云/面经.md",
    "build/sitemap.xml",
    "build/面试.html",
    "build/面试/hr 面.html",
    "docs/计算机网络/4. URL 到 显示内容.md",
    "docs/Linux/4. Linux Crash Course.md",
    "docs/Linux/3. Linux用户管理.md",
    "docs/Linux/[.md"
  ]
}